recommendation_68911/__init__.py
recommendation_68911/apps.py
recommendation_68911/exceptions.py
recommendation_68911/managers.py
recommendation_68911/models.py
recommendation_68911/services.py
recommendation_68911/settings.py
recommendation_68911-0.0.1.dist-info/LICENSE
recommendation_68911-0.0.1.dist-info/METADATA
recommendation_68911-0.0.1.dist-info/WHEEL
recommendation_68911-0.0.1.dist-info/top_level.txt
recommendation_68911-0.0.1.dist-info/RECORD
