Metadata-Version: 2.1
Name: recommendation-68911
Version: 0.0.1
Summary: Package for recommendation system (68911) integration
Home-page: https://github.com/gernathlub/recommendation_68911
Author: Lubomir Gernath
Author-email: lubomir.gernath@student.tuke.sk
License: MIT
Requires-Python: >=3.8
License-File: LICENSE
Requires-Dist: Django (>=3.2)
Requires-Dist: requests (>=2.25)
